squirrel/__init__.py
squirrel/__main__.py
squirrel/gui/__init__.py
squirrel/sps/__init__.py
squirrel/utils/__init__.py
squirrel_pack-1.0.1.dist-info/METADATA
squirrel_pack-1.0.1.dist-info/WHEEL
squirrel_pack-1.0.1.dist-info/top_level.txt
squirrel_pack-1.0.1.dist-info/RECORD
