Metadata-Version: 2.1
Name: squirrel-pack
Version: 1.0.1
Summary: a collection of my scripts and tools :D
Author: Dominik Krenn
Author-email: chipperfluff@gmail.com
